design files/cordic_engine.v
// =============================================================================
// Coordinate Rotation Unit (CRU) for StarCore-1
// EEE4120F HPES Project 2026  |  OrbitEdge-1 Mission
// =============================================================================
//
// ARCHITECTURE: Iterative (folded) CORDIC, rotation mode.
//   Computes cos(theta) and sin(theta) using only shift-and-add arithmetic.
//   No hardware multipliers required.
//
// FIXED-POINT FORMATS
//   theta input : 12-bit signed Q0.11 normalised
//                 Encodes angle as a fraction of 90 degrees:
//                   theta = round( angle_degrees / 90 * 2^11 )
//                 Range: -2048..+2047 -> -90..+90 degrees
//                 Examples:   0 deg -> 0x000
//                            45 deg -> 0x400
//                           -45 deg -> 0xC00
//
//   z register  : 16-bit signed Q0.14 (same normalised units, finer LSB)
//                 Loaded by left-shifting theta 3 bits (Q0.11 -> Q0.14):
//                   z = { theta[11], theta[11:0], 3'b000 }
//
//   atan_rom    : 16-entry x 16-bit, Q0.14 normalised arctangent.
//                 Entry i = round( atan(2^-i) / (pi/2) * 2^14 )
//                 Same unit as z so z +/- atan_rom[i] is valid.
//                 File: atan_rom.mem
//
//   x, y regs   : 16-bit signed Q1.15 (range approx +/-1)
//                 Initialised to K_INV.  After 16 iterations:
//                   x -> cos(theta),  y -> sin(theta)
//
// FSM (Moore, 3 states):
//   IDLE -> ITER : on START; loads x0=K_INV, y0=0, z0=theta_extended
//   ITER         : 16 micro-rotations.  BUSY=1, VALID=0.
//   DONE -> IDLE : latches results, pulses VALID for 1 cycle.  BUSY=0.
//   Total latency: 18 clock cycles from START to VALID.
//
// =============================================================================

module cordic_engine #(
    parameter N_ITER = 16
) (
    input  wire        clk,
    input  wire        rst_n,
    input  wire        start,
    input  wire [11:0] theta,
    output reg  [15:0] cos_result,
    output reg  [15:0] sin_result,
    output reg         busy,
    output reg         valid
);

// ---------------------------------------------------------------------------
// FSM states
// ---------------------------------------------------------------------------
localparam [1:0] IDLE = 2'd0, ITER = 2'd1, DONE = 2'd2;
reg [1:0] state;

// ---------------------------------------------------------------------------
// Iteration counter
// ---------------------------------------------------------------------------
reg [3:0] i;

// ---------------------------------------------------------------------------
// K_INV: CORDIC gain pre-compensation constant
//
// Exact value: K_INV = 1 / prod_{i=0}^{15} sqrt(1 + 2^{-2i})
//            = 0.607253...
//            -> Q1.15 -> round(0.607253 * 32768) = 19898 = 0x4DBA
//
// ---------------------------------------------------------------------------
localparam signed [15:0] K_INV = 16'sh4DB8;

// ---------------------------------------------------------------------------
// Datapath registers
// ---------------------------------------------------------------------------
reg signed [15:0] x;   // cos accumulator, Q1.15
reg signed [15:0] y;   // sin accumulator, Q1.15
reg signed [15:0] z;   // angle accumulator, Q0.14 normalised

// ---------------------------------------------------------------------------
// Arctangent ROM
// Entry i = round( atan(2^-i) / (pi/2) * 2^14 )
// i=0: 0x2000  i=1: 0x12E4  i=2: 0x09FB  i=3: 0x0511  ...
// ---------------------------------------------------------------------------
reg [15:0] atan_rom [0 : N_ITER-1];
initial $readmemh("atan_rom.mem", atan_rom);

// ---------------------------------------------------------------------------
// Arithmetic right-shift combinational helpers
// ---------------------------------------------------------------------------
wire signed [15:0] x_shr = $signed(x) >>> i;
wire signed [15:0] y_shr = $signed(y) >>> i;
wire               d_pos = ~z[15];   // 1 when z >= 0

// ---------------------------------------------------------------------------
// FSM + Datapath
// ---------------------------------------------------------------------------
always @(posedge clk or negedge rst_n) begin
    if (!rst_n) begin
        state      <= IDLE;
        x          <= 16'sd0;
        y          <= 16'sd0;
        z          <= 16'sd0;
        i          <= 4'd0;
        cos_result <= 16'd0;
        sin_result <= 16'd0;
        busy       <= 1'b0;
        valid      <= 1'b0;
    end else begin
        case (state)

            // ----------------------------------------------------------------
            // IDLE: wait for start pulse, keep outputs idle
            // ----------------------------------------------------------------
            IDLE: begin
                busy  <= 1'b0;
                valid <= 1'b0;
                if (start) begin
                    x     <= K_INV;
                    y     <= 16'sd0;
                    // BUG FIX #1: shift theta left 3 to convert Q0.11 -> Q0.14
                    // {theta[11], theta[11:0], 3'b000} = 1+12+3 = 16 bits
                    z     <= $signed({theta[11], theta[11:0], 3'b000});
                    i     <= 4'd0;
                    busy  <= 1'b1;
                    state <= ITER;
                end
            end

            // ----------------------------------------------------------------
            // ITER: perform CORDIC micro-rotation for step i
            // ----------------------------------------------------------------
            ITER: begin
                if (d_pos) begin
                    x <= x - y_shr;
                    y <= y + x_shr;
                    z <= z - $signed({1'b0, atan_rom[i]});
                end else begin
                    x <= x + y_shr;
                    y <= y - x_shr;
                    z <= z + $signed({1'b0, atan_rom[i]});
                end

                i <= i + 4'd1;
                if (i == N_ITER - 1) begin
                    busy  <= 1'b0;
                    state <= DONE;
                end
            end

            // ----------------------------------------------------------------
            // DONE: latch results, pulse VALID, return to IDLE
            // ----------------------------------------------------------------
            DONE: begin
                cos_result <= x;
                sin_result <= y;
                valid      <= 1'b1;
                state      <= IDLE;
            end

            default: state <= IDLE;

        endcase
    end
end

endmodule

sim_tb.v
`timescale 1ns/1ps

module sim_tb;

localparam CLK_PERIOD = 10;
localparam N          = 16;
localparam ERR_THRESH = 20;

reg        clk, rst_n, start;
reg [11:0] theta;
wire [15:0] cos_out, sin_out;
wire        busy, valid;

integer pass_count = 0;
integer fail_count = 0;
integer cycle_count, k;

reg [11:0] test_theta [0:N-1];
reg [15:0] gold_cos   [0:N-1];
reg [15:0] gold_sin   [0:N-1];

cordic_engine #(.N_ITER(16)) DUT (
    .clk(clk), .rst_n(rst_n), .start(start), .theta(theta),
    .cos_result(cos_out), .sin_result(sin_out), .busy(busy), .valid(valid)
);

initial clk = 0;
always #(CLK_PERIOD/2) clk = ~clk;

initial begin
    // Gold values from fixed-point Python model (bit-exact match expected)
    //          theta      cos(Q1.15)  sin(Q1.15)
    test_theta[ 0]=12'h000; gold_cos[ 0]=16'h7FFD; gold_sin[ 0]=16'h0002; //   0deg
    test_theta[ 1]=12'h0E4; gold_cos[ 1]=16'h7E08; gold_sin[ 1]=16'h1648; //  10deg
    test_theta[ 2]=12'h155; gold_cos[ 2]=16'h7BA3; gold_sin[ 2]=16'h211C; //  15deg
    test_theta[ 3]=12'h200; gold_cos[ 3]=16'h7647; gold_sin[ 3]=16'h30FC; //  22.5deg
    test_theta[ 4]=12'h2AB; gold_cos[ 4]=16'h6ED4; gold_sin[ 4]=16'h4005; //  30deg
    test_theta[ 5]=12'h400; gold_cos[ 5]=16'h5A7E; gold_sin[ 5]=16'h5A81; //  45deg
    test_theta[ 6]=12'h555; gold_cos[ 6]=16'h4005; gold_sin[ 6]=16'h6ED4; //  60deg
    test_theta[ 7]=12'h6AB; gold_cos[ 7]=16'h2114; gold_sin[ 7]=16'h7BA5; //  75deg
    test_theta[ 8]=12'h7E9; gold_cos[ 8]=16'h023E; gold_sin[ 8]=16'h7FF5; //  89deg
    test_theta[ 9]=12'hF1C; gold_cos[ 9]=16'h7E09; gold_sin[ 9]=16'hE9B5; // -10deg
    test_theta[10]=12'hEAB; gold_cos[10]=16'h7B9F; gold_sin[10]=16'hDEEC; // -15deg
    test_theta[11]=12'hD55; gold_cos[11]=16'h6ED5; gold_sin[11]=16'hBFFB; // -30deg
    test_theta[12]=12'hC00; gold_cos[12]=16'h5A84; gold_sin[12]=16'hA582; // -45deg
    test_theta[13]=12'hAAB; gold_cos[13]=16'h4006; gold_sin[13]=16'h912C; // -60deg
    test_theta[14]=12'h955; gold_cos[14]=16'h211F; gold_sin[14]=16'h845D; // -75deg
    test_theta[15]=12'h000; gold_cos[15]=16'h7FFD; gold_sin[15]=16'h0002; //   0deg regression
end

task run_test;
    input integer tid;
    integer ec, es;
begin
    theta = test_theta[tid];
    @(posedge clk); #1; start = 1;
    @(posedge clk); #1; start = 0;
    cycle_count = 0;
    while (!valid && cycle_count < 30) begin
        @(posedge clk); #1;
        cycle_count = cycle_count + 1;
    end
    if (!valid) begin
        $display("[TIMEOUT] Test %2d theta=0x%03h", tid, test_theta[tid]);
        fail_count = fail_count + 1;
    end else begin
        ec = abs_diff(cos_out, gold_cos[tid]);
        es = abs_diff(sin_out, gold_sin[tid]);
        if (ec <= ERR_THRESH && es <= ERR_THRESH) begin
            $display("[PASS] Test %2d | theta=0x%03h | cos=0x%04h(err=%0d) sin=0x%04h(err=%0d) | cyc=%0d",
                tid, test_theta[tid], cos_out, ec, sin_out, es, cycle_count);
            pass_count = pass_count + 1;
        end else begin
            $display("[FAIL] Test %2d | theta=0x%03h | cos=0x%04h(exp=0x%04h err=%0d) sin=0x%04h(exp=0x%04h err=%0d)",
                tid, test_theta[tid], cos_out, gold_cos[tid], ec, sin_out, gold_sin[tid], es);
            fail_count = fail_count + 1;
        end
    end
    repeat(3) @(posedge clk);
end
endtask

function integer abs_diff;
    input [15:0] a, b;
    integer d;
begin
    d = $signed(a) - $signed(b);
    abs_diff = (d < 0) ? -d : d;
end
endfunction

initial begin
    $dumpfile("cru_tb.vcd");
    $dumpvars(0, sim_tb);
    $display("==============================================");
    $display("  CRU Simulation  cordic_engine.v");
    $display("==============================================");
    rst_n = 0; start = 0; theta = 0;
    repeat(4) @(posedge clk);
    rst_n = 1;
    repeat(2) @(posedge clk);
    for (k = 0; k < N; k = k + 1) run_test(k);
    $display("==============================================");
    $display("  PASS: %0d  FAIL: %0d  TOTAL: %0d", pass_count, fail_count, N);
    if (fail_count == 0) $display("  *** ALL TESTS PASSED ***");
    $display("==============================================");
    $finish;
end

endmodule

verification files/cru_tb.vcd
$date
	Sun May 17 23:20:08 2026
$end
$version
	Icarus Verilog
$end
$timescale
	1ps
$end
$scope module sim_tb $end
$var wire 1 ! valid $end
$var wire 16 " sin_out [15:0] $end
$var wire 16 # cos_out [15:0] $end
$var wire 1 $ busy $end
$var parameter 32 % CLK_PERIOD $end
$var parameter 32 & ERR_THRESH $end
$var parameter 32 ' N $end
$var reg 1 ( clk $end
$var reg 1 ) rst_n $end
$var reg 1 * start $end
$var reg 12 + theta [11:0] $end
$var integer 32 , cycle_count [31:0] $end
$var integer 32 - fail_count [31:0] $end
$var integer 32 . k [31:0] $end
$var integer 32 / pass_count [31:0] $end
$scope function abs_diff $end
$var reg 16 0 a [15:0] $end
$var reg 16 1 b [15:0] $end
$var integer 32 2 d [31:0] $end
$upscope $end
$scope module DUT $end
$var wire 1 ( clk $end
$var wire 1 3 d_pos $end
$var wire 1 ) rst_n $end
$var wire 1 * start $end
$var wire 12 4 theta [11:0] $end
$var wire 16 5 y_shr [15:0] $end
$var wire 16 6 x_shr [15:0] $end
$var parameter 2 7 DONE $end
$var parameter 2 8 IDLE $end
$var parameter 2 9 ITER $end
$var parameter 16 : K_INV $end
$var parameter 32 ; N_ITER $end
$var reg 1 $ busy $end
$var reg 16 < cos_result [15:0] $end
$var reg 4 = i [3:0] $end
$var reg 16 > sin_result [15:0] $end
$var reg 2 ? state [1:0] $end
$var reg 1 ! valid $end
$var reg 16 @ x [15:0] $end
$var reg 16 A y [15:0] $end
$var reg 16 B z [15:0] $end
$upscope $end
$scope task run_test $end
$var integer 32 C ec [31:0] $end
$var integer 32 D es [31:0] $end
$var integer 32 E tid [31:0] $end
$upscope $end
$upscope $end
$enddefinitions $end
$comment Show the parameter values. $end
$dumpall
b10000 ;
b100110110111000 :
b1 9
b0 8
b10 7
b10000 '
b10100 &
b1010 %
$end
#0
$dumpvars
bx E
bx D
bx C
b0 B
b0 A
b0 @
b0 ?
b0 >
b0 =
b0 <
b0 6
b0 5
b0 4
13
bx 2
bx 1
bx 0
b0 /
bx .
b0 -
bx ,
b0 +
0*
0)
0(
0$
b0 #
b0 "
0!
$end
#5000
1(
#10000
0(
#15000
1(
#20000
0(
#25000
1(
#30000
0(
#35000
1)
1(
#40000
0(
#45000
1(
#50000
0(
#55000
b0 E
b0 .
1(
#60000
0(
#65000
1(
#66000
1*
#70000
0(
#75000
b1 ?
1$
b100110110111000 6
b100110110111000 @
1(
#76000
b0 ,
0*
#80000
0(
#85000
03
b10011011011100 6
b1 =
b1110000000000000 B
b10011011011100 5
b100110110111000 A
1(
#86000
b1 ,
#90000
0(
#95000
b10 =
b1111001011100100 B
b100110110111 5
b10011011011100 A
b1110100100101 6
b111010010010100 @
1(
#96000
b10 ,
#100000
0(
#105000
b11 =
b1111110011011111 B
b100110110 5
b100110110111 A
b111111001001 6
b111111001001011 @
1(
#106000
b11 ,
#110000
0(
#115000
13
b100 =
b111110000 B
b1111111110011110 5
b1111100111101110 A
b11111111000 6
b111111110000001 @
1(
#116000
b100 ,
#120000
0(
#125000
03
b101 =
b1111111101100101 B
b1111 5
b111100110 A
b1111111111 6
b111111111100011 @
1(
#126000
b101 ,
#130000
0(
#135000
13
b111111111 6
b110 =
b10101011 B
b1111111111110111 5
b1111110111100111 A
b111111111110010 @
1(
#136000
b110 ,
#140000
0(
#145000
b11111111 6
b111 =
b1000 B
b1111111111111111 5
b1111111111100110 A
b111111111111011 @
1(
#146000
b111 ,
#150000
0(
#155000
03
b1111111 6
b1000 =
b1111111110110111 B
b0 5
b11100101 A
b111111111111100 @
1(
#156000
b1000 ,
#160000
0(
#165000
b111111 6
b1001 =
b1111111111100000 B
b1100110 A
1(
#166000
b1001 ,
#170000
0(
#175000
b11111 6
b1010 =
b1111111111110100 B
b100111 A
1(
#176000
b1010 ,
#180000
0(
#185000
b1111 6
b1011 =
b1111111111111110 B
b1000 A
1(
#186000
b1011 ,
#190000
0(
#195000
13
b111 6
b1100 =
b11 B
b1111111111111111 5
b1111111111111001 A
1(
#196000
b1100 ,
#200000
0(
#205000
b11 6
b1101 =
b0 B
b0 5
b0 A
b111111111111101 @
1(
#206000
b1101 ,
#210000
0(
#215000
03
b1 6
b1110 =
b1111111111111111 B
b11 A
1(
#216000
b1110 ,
#220000
0(
#225000
13
b0 6
b1111 =
b0 B
b10 A
1(
#226000
b1111 ,
#230000
0(
#235000
b10 ?
0$
b111111111111101 6
b10 5
b0 =
1(
#236000
b10000 ,
#240000
0(
#245000
b0 ?
1!
b10 "
b10 >
b111111111111101 #
b111111111111101 <
1(
#246000
b1 /
b0 D
b0 C
b0 2
b10 0
b10 1
b10001 ,
#250000
0(
#255000
0!
1(
#260000
0(
#265000
1(
#270000
0(
#275000
b11100100 +
b11100100 4
b1 E
b1 .
1(
#280000
0(
#285000
1(
#286000
1*
#290000
0(
#295000
b1 ?
1$
b11100100000 B
b0 5
b0 A
b100110110111000 6
b100110110111000 @
1(
#296000
b0 ,
0*
#300000
0(
#305000
03
b10011011011100 6
b1 =
b1110011100100000 B
b10011011011100 5
b100110110111000 A
1(
#306000
b1 ,
#310000
0(
#315000
b10 =
b1111101000000100 B
b100110110111 5
b10011011011100 A
b1110100100101 6
b111010010010100 @
1(
#316000
b10 ,
#320000
0(
#325000
13
b11 =
b1111111111 B
b100110110 5
b100110110111 A
b111111001001 6
b111111001001011 @
1(
#326000
b11 ,
#330000
0(
#335000
03
b100 =
b1111111011101110 B
b110011000 5
b1100110000000 A
b11111010001 6
b111110100010101 @
1(
#336000
b100 ,
#340000
0(
#345000
13
b101 =
b101111001 B
b10001101 5
b1000110101111 A
b1111110101 6
b111111010101101 @
1(
#346000
b101 ,
#350000
0(
#355000
b110 =
b110011 B
b1010110 5
b1010110100100 A
b111111000 6
b111111000100000 @
1(
#356000
b110 ,
#360000
0(
#365000
03
b111 =
b1111111110010000 B
b101111 5
b1011110011100 A
b11111011 6
b111110111001010 @
1(
#366000
b111 ,
#370000
0(
#375000
b1111101 6
b1000 =
b1111111111100001 B
b10110 5
b1011010100001 A
b111110111111001 @
1(
#376000
b1000 ,
#380000
0(
#385000
13
b1011 5
b1001 =
b1010 B
b1011000100100 A
b111111 6
b111111000001111 @
1(
#386000
b1001 ,
#390000
0(
#395000
03
b11111 6
b101 5
b1010 =
b1111111111110110 B
b1011001100011 A
b111111000000100 @
1(
#396000
b1010 ,
#400000
0(
#405000
13
b1111 6
b10 5
b1011 =
b0 B
b1011001000100 A
b111111000001001 @
1(
#406000
b1011 ,
#410000
0(
#415000
03
b111 6
b1 5
b1100 =
b1111111111111011 B
b1011001010011 A
b111111000000111 @
1(
#416000
b1100 ,
#420000
0(
#425000
b11 6
b0 5
b1101 =
b1111111111111110 B
b1011001001100 A
b111111000001000 @
1(
#426000
b1101 ,
#430000
0(
#435000
b1 6
b1110 =
b1111111111111111 B
b1011001001001 A
1(
#436000
b1110 ,
#440000
0(
#445000
13
b0 6
b1111 =
b0 B
b1011001001000 A
1(
#446000
b1111 ,
#450000
0(
#455000
b10 ?
0$
b111111000001000 6
b1011001001000 5
b0 =
1(
#456000
b10000 ,
#460000
0(
#465000
b0 ?
1!
b1011001001000 "
b1011001001000 >
b111111000001000 #
b111111000001000 <
1(
#466000
b10 /
b1011001001000 0
b1011001001000 1
b10001 ,
#470000
0(
#475000
0!
1(
#480000
0(
#485000
1(
#490000
0(
#495000
b101010101 +
b101010101 4
b10 E
b10 .
1(
#500000
0(
#505000
1(
#506000
1*
#510000
0(
#515000
b1 ?
1$
b101010101000 B
b0 5
b0 A
b100110110111000 6
b100110110111000 @
1(
#516000
b0 ,
0*
#520000
0(
#525000
03
b10011011011100 6
b1 =
b1110101010101000 B
b10011011011100 5
b100110110111000 A
1(
#526000
b1 ,
#530000
0(
#535000
b10 =
b1111110110001100 B
b100110110111 5
b10011011011100 A
b1110100100101 6
b111010010010100 @
1(
#536000
b10 ,
#540000
0(
#545000
13
b11 =
b11110000111 B
b100110110 5
b100110110111 A
b111111001001 6
b111111001001011 @
1(
#546000
b11 ,
#550000
0(
#555000
b100 =
b1001110110 B
b110011000 5
b1100110000000 A
b11111010001 6
b111110100010101 @
1(
#556000
b100 ,
#560000
0(
#565000
03
b101 =
b1111111111101011 B
b100001010 5
b10000101010001 A
b1111011011 6
b111101101111101 @
1(
#566000
b101 ,
#570000
0(
#575000
13
b110 =
b100110001 B
b1110101 5
b1110101110110 A
b111110010 6
b111110010000111 @
1(
#576000
b110 ,
#580000
0(
#585000
b111 =
b10001110 B
b111110 5
b1111101101000 A
b11111000 6
b111110000010010 @
1(
#586000
b111 ,
#590000
0(
#595000
b1000 =
b111101 B
b100000 5
b10000001100000 A
b1111011 6
b111101111010100 @
1(
#596000
b1000 ,
#600000
0(
#605000
b111101 6
b10000 5
b1001 =
b10100 B
b10000011011011 A
b111101110110100 @
1(
#606000
b1001 ,
#610000
0(
#615000
b11110 6
b1000 5
b1010 =
b0 B
b10000100011000 A
b111101110100100 @
1(
#616000
b1010 ,
#620000
0(
#625000
03
b1111 6
b100 5
b1011 =
b1111111111110110 B
b10000100110110 A
b111101110011100 @
1(
#626000
b1011 ,
#630000
0(
#635000
b111 6
b10 5
b1100 =
b1111111111111011 B
b10000100100111 A
b111101110100000 @
1(
#636000
b1100 ,
#640000
0(
#645000
b11 6
b1 5
b1101 =
b1111111111111110 B
b10000100100000 A
b111101110100010 @
1(
#646000
b1101 ,
#650000
0(
#655000
b1 6
b0 5
b1110 =
b1111111111111111 B
b10000100011101 A
b111101110100011 @
1(
#656000
b1110 ,
#660000
0(
#665000
13
b0 6
b1111 =
b0 B
b10000100011100 A
1(
#666000
b1111 ,
#670000
0(
#675000
b10 ?
0$
b111101110100011 6
b10000100011100 5
b0 =
1(
#676000
b10000 ,
#680000
0(
#685000
b0 ?
1!
b10000100011100 "
b10000100011100 >
b111101110100011 #
b111101110100011 <
1(
#686000
b11 /
b10000100011100 0
b10000100011100 1
b10001 ,
#690000
0(
#695000
0!
1(
#700000
0(
#705000
1(
#710000
0(
#715000
b1000000000 +
b1000000000 4
b11 E
b11 .
1(
#720000
0(
#725000
1(
#726000
1*
#730000
0(
#735000
b1 ?
1$
b1000000000000 B
b0 5
b0 A
b100110110111000 6
b100110110111000 @
1(
#736000
b0 ,
0*
#740000
0(
#745000
03
b10011011011100 6
b1 =
b1111000000000000 B
b10011011011100 5
b100110110111000 A
1(
#746000
b1 ,
#750000
0(
#755000
13
b10 =
b1011100100 B
b100110110111 5
b10011011011100 A
b1110100100101 6
b111010010010100 @
1(
#756000
b10 ,
#760000
0(
#765000
03
b11 =
b1111100011101001 B
b100010000000 5
b100010000000001 A
b110101011011 6
b110101011011101 @
1(
#766000
b11 ,
#770000
0(
#775000
b100 =
b1111110111111010 B
b1101101010 5
b11011010100110 A
b11100110101 6
b111001101011101 @
1(
#776000
b100 ,
#780000
0(
#785000
13
b101 =
b10000101 B
b101111011 5
b10111101110001 A
b1110110110 6
b111011011000111 @
1(
#786000
b101 ,
#790000
0(
#795000
03
b110 =
b1111111100111111 B
b11001100 5
b11001100100111 A
b111010101 6
b111010101001100 @
1(
#796000
b110 ,
#800000
0(
#805000
b111 =
b1111111111100010 B
b1100010 5
b11000101010010 A
b11101100 6
b111011000011000 @
1(
#806000
b111 ,
#810000
0(
#815000
13
b1110110 6
b1000 =
b110011 B
b110000 5
b11000001100110 A
b111011001111010 @
1(
#816000
b1000 ,
#820000
0(
#825000
b111011 6
b11000 5
b1001 =
b1010 B
b11000011011100 A
b111011001001010 @
1(
#826000
b1001 ,
#830000
0(
#835000
03
b11101 6
b1100 5
b1010 =
b1111111111110110 B
b11000100010111 A
b111011000110010 @
1(
#836000
b1010 ,
#840000
0(
#845000
13
b1110 6
b110 5
b1011 =
b0 B
b11000011111010 A
b111011000111110 @
1(
#846000
b1011 ,
#850000
0(
#855000
03
b111 6
b11 5
b1100 =
b1111111111111011 B
b11000100001000 A
b111011000111000 @
1(
#856000
b1100 ,
#860000
0(
#865000
b11 6
b1 5
b1101 =
b1111111111111110 B
b11000100000001 A
b111011000111011 @
1(
#866000
b1101 ,
#870000
0(
#875000
b1 6
b0 5
b1110 =
b1111111111111111 B
b11000011111110 A
b111011000111100 @
1(
#876000
b1110 ,
#880000
0(
#885000
13
b0 6
b1111 =
b0 B
b11000011111101 A
1(
#886000
b1111 ,
#890000
0(
#895000
b10 ?
0$
b111011000111100 6
b11000011111101 5
b0 =
1(
#896000
b10000 ,
#900000
0(
#905000
b0 ?
1!
b11000011111101 "
b11000011111101 >
b111011000111100 #
b111011000111100 <
1(
#906000
b100 /
b1 D
b1011 C
b1 2
b11000011111101 0
b11000011111100 1
b10001 ,
#910000
0(
#915000
0!
1(
#920000
0(
#925000
1(
#930000
0(
#935000
b1010101011 +
b1010101011 4
b100 E
b100 .
1(
#940000
0(
#945000
1(
#946000
1*
#950000
0(
#955000
b1 ?
1$
b1010101011000 B
b0 5
b0 A
b100110110111000 6
b100110110111000 @
1(
#956000
b0 ,
0*
#960000
0(
#965000
03
b10011011011100 6
b1 =
b1111010101011000 B
b10011011011100 5
b100110110111000 A
1(
#966000
b1 ,
#970000
0(
#975000
13
b10 =
b100000111100 B
b100110110111 5
b10011011011100 A
b1110100100101 6
b111010010010100 @
1(
#976000
b10 ,
#980000
0(
#985000
03
b11 =
b1111111001000001 B
b100010000000 5
b100010000000001 A
b110101011011 6
b110101011011101 @
1(
#986000
b11 ,
#990000
0(
#995000
13
b100 =
b1101010010 B
b1101101010 5
b11011010100110 A
b11100110101 6
b111001101011101 @
1(
#996000
b100 ,
#1000000
0(
#1005000
b101 =
b11000111 B
b111101110 5
b11110111011011 A
b1101111111 6
b110111111110011 @
1(
#1006000
b101 ,
#1010000
0(
#1015000
03
b110 =
b1111111110000001 B
b100000101 5
b100000101011010 A
b110111000 6
b110111000000101 @
1(
#1016000
b110 ,
#1020000
0(
#1025000
13
b111 =
b100100 B
b1111111 5
b11111110100010 A
b11011110 6
b110111100001010 @
1(
#1026000
b111 ,
#1030000
0(
#1035000
03
b1000 =
b1111111111010011 B
b1000000 5
b100000010000000 A
b1101110 6
b110111010001011 @
1(
#1036000
b1000 ,
#1040000
0(
#1045000
b110111 6
b100000 5
b1001 =
b1111111111111100 B
b100000000010010 A
b110111011001011 @
1(
#1046000
b1001 ,
#1050000
0(
#1055000
13
b11011 6
b1010 =
b10000 B
b1111 5
b11111111011011 A
b110111011101011 @
1(
#1056000
b1010 ,
#1060000
0(
#1065000
b1101 6
b111 5
b1011 =
b110 B
b11111111110110 A
b110111011011100 @
1(
#1066000
b1011 ,
#1070000
0(
#1075000
b110 6
b1100 =
b1 B
b100 5
b100000000000011 A
b110111011010101 @
1(
#1076000
b1100 ,
#1080000
0(
#1085000
03
b11 6
b10 5
b1101 =
b1111111111111110 B
b100000000001001 A
b110111011010001 @
1(
#1086000
b1101 ,
#1090000
0(
#1095000
b1 6
b1 5
b1110 =
b1111111111111111 B
b100000000000110 A
b110111011010011 @
1(
#1096000
b1110 ,
#1100000
0(
#1105000
13
b0 6
b0 5
b1111 =
b0 B
b100000000000101 A
b110111011010100 @
1(
#1106000
b1111 ,
#1110000
0(
#1115000
b10 ?
0$
b110111011010100 6
b100000000000101 5
b0 =
1(
#1116000
b10000 ,
#1120000
0(
#1125000
b0 ?
1!
b100000000000101 "
b100000000000101 >
b110111011010100 #
b110111011010100 <
1(
#1126000
b101 /
b0 D
b0 C
b0 2
b100000000000101 0
b100000000000101 1
b10001 ,
#1130000
0(
#1135000
0!
1(
#1140000
0(
#1145000
1(
#1150000
0(
#1155000
b10000000000 +
b10000000000 4
b101 E
b101 .
1(
#1160000
0(
#1165000
1(
#1166000
1*
#1170000
0(
#1175000
b1 ?
1$
b10000000000000 B
b0 5
b0 A
b100110110111000 6
b100110110111000 @
1(
#1176000
b0 ,
0*
#1180000
0(
#1185000
b10011011011100 6
b1 =
b0 B
b10011011011100 5
b100110110111000 A
1(
#1186000
b1 ,
#1190000
0(
#1195000
03
b10 =
b1110110100011100 B
b1110100100101 5
b111010010010100 A
b100110110111 6
b10011011011100 @
1(
#1196000
b10 ,
#1200000
0(
#1205000
b11 =
b1111011100010111 B
b110101011011 5
b110101011011101 A
b100010000000 6
b100010000000001 @
1(
#1206000
b11 ,
#1210000
0(
#1215000
b100 =
b1111110000101000 B
b11000100101 5
b110001001011101 A
b10100010101 6
b101000101011100 @
1(
#1216000
b100 ,
#1220000
0(
#1225000
b101 =
b1111111010110011 B
b1011101010 5
b101110101001000 A
b1010111100 6
b101011110000001 @
1(
#1226000
b101 ,
#1230000
0(
#1235000
b110 =
b1111111111111001 B
b101101010 5
b101101010001100 A
b101101001 6
b101101001101011 @
1(
#1236000
b110 ,
#1240000
0(
#1245000
13
b111 =
b10011100 B
b10110010 5
b101100100100011 A
b10110111 6
b101101111010101 @
1(
#1246000
b111 ,
#1250000
0(
#1255000
b1000 =
b1001011 B
b1011001 5
b101100111011010 A
b1011011 6
b101101100100011 @
1(
#1256000
b1000 ,
#1260000
0(
#1265000
b1001 =
b100010 B
b101101 5
b101101000110101 A
b101101 6
b101101011001010 @
1(
#1266000
b1001 ,
#1270000
0(
#1275000
b10110 6
b10110 5
b1010 =
b1110 B
b101101001100010 A
b101101010011101 @
1(
#1276000
b1010 ,
#1280000
0(
#1285000
b1011 6
b1011 5
b1011 =
b100 B
b101101001111000 A
b101101010000111 @
1(
#1286000
b1011 ,
#1290000
0(
#1295000
03
b101 6
b101 5
b1100 =
b1111111111111111 B
b101101010000011 A
b101101001111100 @
1(
#1296000
b1100 ,
#1300000
0(
#1305000
13
b10 6
b10 5
b1101 =
b10 B
b101101001111110 A
b101101010000001 @
1(
#1306000
b1101 ,
#1310000
0(
#1315000
b1 6
b1 5
b1110 =
b1 B
b101101010000000 A
b101101001111111 @
1(
#1316000
b1110 ,
#1320000
0(
#1325000
b0 6
b0 5
b1111 =
b0 B
b101101010000001 A
b101101001111110 @
1(
#1326000
b1111 ,
#1330000
0(
#1335000
b10 ?
0$
b101101001111110 6
b101101010000001 5
b0 =
1(
#1336000
b10000 ,
#1340000
0(
#1345000
b0 ?
1!
b101101010000001 "
b101101010000001 >
b101101001111110 #
b101101001111110 <
1(
#1346000
b110 /
b101101010000001 0
b101101010000001 1
b10001 ,
#1350000
0(
#1355000
0!
1(
#1360000
0(
#1365000
1(
#1370000
0(
#1375000
b10101010101 +
b10101010101 4
b110 E
b110 .
1(
#1380000
0(
#1385000
1(
#1386000
1*
#1390000
0(
#1395000
b1 ?
1$
b10101010101000 B
b0 5
b0 A
b100110110111000 6
b100110110111000 @
1(
#1396000
b0 ,
0*
#1400000
0(
#1405000
b10011011011100 6
b1 =
b101010101000 B
b10011011011100 5
b100110110111000 A
1(
#1406000
b1 ,
#1410000
0(
#1415000
03
b10 =
b1111011111000100 B
b1110100100101 5
b111010010010100 A
b100110110111 6
b10011011011100 @
1(
#1416000
b10 ,
#1420000
0(
#1425000
13
b11 =
b110111111 B
b110101011011 5
b110101011011101 A
b100010000000 6
b100010000000001 @
1(
#1426000
b11 ,
#1430000
0(
#1435000
03
b100 =
b1111110010101110 B
b11100110101 5
b111001101011101 A
b1101101010 6
b11011010100110 @
1(
#1436000
b100 ,
#1440000
0(
#1445000
b101 =
b1111111100111001 B
b1101111111 5
b110111111110011 A
b111101110 6
b11110111011011 @
1(
#1446000
b101 ,
#1450000
0(
#1455000
13
b110 =
b1111111 B
b110111000 5
b110111000000101 A
b100000101 6
b100000101011010 @
1(
#1456000
b110 ,
#1460000
0(
#1465000
03
b111 =
b1111111111011100 B
b11011110 5
b110111100001010 A
b1111111 6
b11111110100010 @
1(
#1466000
b111 ,
#1470000
0(
#1475000
13
b1000 =
b101101 B
b1101110 5
b110111010001011 A
b1000000 6
b100000010000000 @
1(
#1476000
b1000 ,
#1480000
0(
#1485000
b100000 6
b110111 5
b1001 =
b100 B
b110111011001011 A
b100000000010010 @
1(
#1486000
b1001 ,
#1490000
0(
#1495000
03
b11011 5
b1010 =
b1111111111110000 B
b110111011101011 A
b1111 6
b11111111011011 @
1(
#1496000
b1010 ,
#1500000
0(
#1505000
b111 6
b1101 5
b1011 =
b1111111111111010 B
b110111011011100 A
b11111111110110 @
1(
#1506000
b1011 ,
#1510000
0(
